apexnova/__init__.py
apexnova/entity/__init__.py
apexnova/entity/entity_pb2.py
apexnova/entity/entity_pb2.pyi
apexnova/entity/entity_pb2_grpc.py
apexnova/entity/entity_service_pb2.py
apexnova/entity/entity_service_pb2.pyi
apexnova/entity/entity_service_pb2_grpc.py
apexnova/identity/__init__.py
apexnova/identity/account/__init__.py
apexnova/identity/account/account_pb2.py
apexnova/identity/account/account_pb2.pyi
apexnova/identity/account/account_pb2_grpc.py
apexnova/identity/account/account_service_pb2.py
apexnova/identity/account/account_service_pb2.pyi
apexnova/identity/account/account_service_pb2_grpc.py
apexnova/identity/user/__init__.py
apexnova/identity/user/user_pb2.py
apexnova/identity/user/user_pb2.pyi
apexnova/identity/user/user_pb2_grpc.py
apexnova/identity/user/user_service_pb2.py
apexnova/identity/user/user_service_pb2.pyi
apexnova/identity/user/user_service_pb2_grpc.py
apexnova/market/__init__.py
apexnova/market/market_pb2.py
apexnova/market/market_pb2.pyi
apexnova/market/market_pb2_grpc.py
apexnova/market/market_service_pb2.py
apexnova/market/market_service_pb2.pyi
apexnova/market/market_service_pb2_grpc.py
apexnova/notification/__init__.py
apexnova/notification/notification_pb2.py
apexnova/notification/notification_pb2.pyi
apexnova/notification/notification_pb2_grpc.py
apexnova/notification/notification_service_pb2.py
apexnova/notification/notification_service_pb2.pyi
apexnova/notification/notification_service_pb2_grpc.py
apexnova/stub/__init__.py
apexnova/stub/authorization_context_pb2.py
apexnova/stub/authorization_context_pb2.pyi
apexnova/stub/authorization_context_pb2_grpc.py
apexnova/stub/response_pb2.py
apexnova/stub/response_pb2.pyi
apexnova/stub/response_pb2_grpc.py
apexnova/stub/async/__init__.py
apexnova/stub/async/async_processing.py
apexnova/stub/authorization/__init__.py
apexnova/stub/authorization/authorization_rule.py
apexnova/stub/authorization/authorization_status.py
apexnova/stub/authorization/enhanced_authorization_model.py
apexnova-1.2.526.dist-info/METADATA
apexnova-1.2.526.dist-info/WHEEL
apexnova-1.2.526.dist-info/top_level.txt
apexnova-1.2.526.dist-info/RECORD
