Metadata-Version: 2.4
Name: apexnova
Version: 1.2.526
Summary: ApexNova gRPC stub library with authorization and telemetry support
Home-page: https://github.com/apexnova-vc/proto
Author: Apex Nova
Author-email: ApexNova Team <team@apexnova.com>
License-Expression: MIT
Project-URL: Homepage, https://github.com/apexnova/proto
Project-URL: Documentation, https://github.com/apexnova/proto/blob/main/stub/python/README.md
Project-URL: Repository, https://github.com/apexnova/proto
Project-URL: Bug Tracker, https://github.com/apexnova/proto/issues
Keywords: grpc,protobuf,azure,telemetry,graph,authorization
Classifier: Development Status :: 4 - Beta
Classifier: Intended Audience :: Developers
Classifier: Programming Language :: Python :: 3
Classifier: Programming Language :: Python :: 3.8
Classifier: Programming Language :: Python :: 3.9
Classifier: Programming Language :: Python :: 3.10
Classifier: Programming Language :: Python :: 3.11
Classifier: Programming Language :: Python :: 3.12
Classifier: Programming Language :: Python :: 3.13
Classifier: Topic :: Software Development :: Libraries :: Python Modules
Classifier: Topic :: Internet :: WWW/HTTP :: HTTP Servers
Classifier: Topic :: System :: Distributed Computing
Requires-Python: >=3.8
Requires-Dist: grpcio>=1.50.0
Requires-Dist: grpcio-tools>=1.50.0
Requires-Dist: protobuf>=4.0.0
Requires-Dist: azure-monitor-opentelemetry>=1.0.0
Requires-Dist: opentelemetry-api>=1.20.0
Requires-Dist: opentelemetry-sdk>=1.20.0
Requires-Dist: gremlinpython>=3.6.0
Requires-Dist: setuptools>=61.0
Requires-Dist: twine>=4.0.0
Requires-Dist: build>=0.10.0
Requires-Dist: pytest>=7.0.0
Requires-Dist: black>=22.0.0
Requires-Dist: mypy>=1.0.0
Requires-Dist: pytest-asyncio>=0.21.0
Provides-Extra: minimal
Requires-Dist: grpcio>=1.50.0; extra == "minimal"
Requires-Dist: protobuf>=4.0.0; extra == "minimal"
Provides-Extra: azure
Requires-Dist: azure-monitor-opentelemetry>=1.0.0; extra == "azure"
Requires-Dist: opentelemetry-api>=1.20.0; extra == "azure"
Requires-Dist: opentelemetry-sdk>=1.20.0; extra == "azure"
Provides-Extra: graph
Requires-Dist: gremlinpython>=3.6.0; extra == "graph"
Provides-Extra: dev
Requires-Dist: pytest>=7.0.0; extra == "dev"
Requires-Dist: black>=22.0.0; extra == "dev"
Requires-Dist: mypy>=1.0.0; extra == "dev"
Requires-Dist: pytest-asyncio>=0.21.0; extra == "dev"
Requires-Dist: setuptools>=61.0; extra == "dev"
Requires-Dist: twine>=4.0.0; extra == "dev"
Requires-Dist: build>=0.10.0; extra == "dev"
Provides-Extra: all
Requires-Dist: azure-monitor-opentelemetry>=1.0.0; extra == "all"
Requires-Dist: opentelemetry-api>=1.20.0; extra == "all"
Requires-Dist: opentelemetry-sdk>=1.20.0; extra == "all"
Requires-Dist: gremlinpython>=3.6.0; extra == "all"
Dynamic: author
Dynamic: home-page
Dynamic: requires-python
